jupyterlab_code_cell_collapser/__init__.py
jupyterlab_code_cell_collapser/_version.py
jupyterlab_code_cell_collapser/labextension/build_log.json
jupyterlab_code_cell_collapser/labextension/package.json
jupyterlab_code_cell_collapser/labextension/static/lib_index_js.4436f86a95986c2bd37f.js
jupyterlab_code_cell_collapser/labextension/static/lib_index_js.4436f86a95986c2bd37f.js.map
jupyterlab_code_cell_collapser/labextension/static/remoteEntry.3df7ac80e6c14a8443ba.js
jupyterlab_code_cell_collapser/labextension/static/remoteEntry.3df7ac80e6c14a8443ba.js.map
jupyterlab_code_cell_collapser/labextension/static/style.js
jupyterlab_code_cell_collapser/labextension/static/style_index_js.e35636571b9ae514d8f5.js
jupyterlab_code_cell_collapser/labextension/static/style_index_js.e35636571b9ae514d8f5.js.map
jupyterlab_code_cell_collapser/labextension/static/vendors-node_modules_css-loader_dist_runtime_api_js-node_modules_css-loader_dist_runtime_cssW-926fd9.97e43e754a1ae2bb751b.js
jupyterlab_code_cell_collapser/labextension/static/vendors-node_modules_css-loader_dist_runtime_api_js-node_modules_css-loader_dist_runtime_cssW-926fd9.97e43e754a1ae2bb751b.js.map
jupyterlab_code_cell_collapser-1.0.0.data/data/share/jupyter/labextensions/@epi2melabs/jupyterlab-code-cell-collapser/build_log.json
jupyterlab_code_cell_collapser-1.0.0.data/data/share/jupyter/labextensions/@epi2melabs/jupyterlab-code-cell-collapser/install.json
jupyterlab_code_cell_collapser-1.0.0.data/data/share/jupyter/labextensions/@epi2melabs/jupyterlab-code-cell-collapser/package.json
jupyterlab_code_cell_collapser-1.0.0.data/data/share/jupyter/labextensions/@epi2melabs/jupyterlab-code-cell-collapser/static/lib_index_js.4436f86a95986c2bd37f.js
jupyterlab_code_cell_collapser-1.0.0.data/data/share/jupyter/labextensions/@epi2melabs/jupyterlab-code-cell-collapser/static/lib_index_js.4436f86a95986c2bd37f.js.map
jupyterlab_code_cell_collapser-1.0.0.dist-info/LICENSE
jupyterlab_code_cell_collapser-1.0.0.dist-info/METADATA
jupyterlab_code_cell_collapser-1.0.0.dist-info/WHEEL
jupyterlab_code_cell_collapser-1.0.0.dist-info/top_level.txt
jupyterlab_code_cell_collapser-1.0.0.dist-info/RECORD
